abstract/Edge.py
abstract/Graph.py
abstract/Node.py
abstract/_BasicGraph.py
abstract/_GraphObj.py
abstract/_GraphWithoutDisplay.py
abstract/__init__.py
abstract/get_ancestors.py
abstract/get_descendants.py
abstract/parse_indentations_function.py
abstract/styling/EdgeStyle.py
abstract/styling/NodeStyle.py
abstract/styling/__init__.py
abstract/styling/get_least_used_colour.py
abstract/styling/inherit_style.py
abstract/styling/is_root_or_parents_are_in_loop.py
abstract/styling/stylize_edges_based_on_nodes.py
abstract/styling/stylize_randomly.py
abstract/styling/stylize_with_pensieve.py
abstract-2025.2.17.0.dist-info/METADATA
abstract-2025.2.17.0.dist-info/WHEEL
abstract-2025.2.17.0.dist-info/top_level.txt
abstract-2025.2.17.0.dist-info/zip-safe
abstract-2025.2.17.0.dist-info/RECORD
