Metadata-Version: 2.2
Name: abstract
Version: 2025.2.17.0
Summary: Python library for creating and drawing graphs and taking advantage of graph properties
Home-page: https://github.com/idin/abstract
Author: Idin
Author-email: py@idin.ca
License: Conditional Freedom License (CFL-1.0)
Keywords: graph
Classifier: Development Status :: 3 - Alpha
Classifier: Intended Audience :: Developers
Classifier: License :: Other/Proprietary License
Classifier: Programming Language :: Python :: 3 :: Only
Classifier: Programming Language :: Python :: 3.6
Classifier: Programming Language :: Python :: 3.7
Classifier: Topic :: Software Development :: Libraries :: Python Modules
Requires-Python: ~=3.6
Requires-Dist: graphviz
Requires-Dist: base32hex
Requires-Dist: colouration
Dynamic: author
Dynamic: author-email
Dynamic: classifier
Dynamic: description
Dynamic: description-content-type
Dynamic: home-page
Dynamic: keywords
Dynamic: license
Dynamic: requires-dist
Dynamic: requires-python
Dynamic: summary
